nbcc_loading/__init__.py
nbcc_loading/loading_data.py
nbcc_loading/seismic.py
nbcc_loading/snow.py
nbcc_loading/wind.py
nbcc_loading/data/snow-2015.pkl
nbcc_loading/data/snow-2020.pkl
nbcc_loading/data/wind-2015.pkl
nbcc_loading/data/wind-2020.pkl
nbcc_loading-0.0.2.dist-info/LICENSE
nbcc_loading-0.0.2.dist-info/WHEEL
nbcc_loading-0.0.2.dist-info/METADATA
nbcc_loading-0.0.2.dist-info/RECORD
