Metadata-Version: 2.1
Name: nbcc_loading
Version: 0.0.2
Summary: NBCC Loadings
Author-email: Arun Kishore <pypi@rpakishore.co.in>
Requires-Python: >=3.9
Classifier: License :: OSI Approved :: MIT License
Requires-Dist: pandas
Requires-Dist: pytest
Project-URL: Home, https://github.com/rpakishore/nbcc-loading
